{
  "properties": {
    "id": {
      "type": "long"
    },
    "image": {
      "type": "keyword",
      "index": false
    },
    "writerId": {
      "type": "long"
    },
    "writerNickname": {
      "type": "keyword"
    },
    "writerProfileImage": {
      "type": "keyword",
      "index": false
    },
    "title": {
      "type": "text",
      "analyzer": "nori"
    },
    "description": {
      "type": "text",
      "analyzer": "nori"
    },
    "tags": {
      "type": "text",
      "analyzer": "nori"
    },
    "category": {
      "type": "keyword"
    },
    "likeCount": {
      "type": "long"
    },
    "viewCount": {
      "type": "long"
    },
    "createdAt": {
      "type": "date",
      "format": "yyyy-MM-dd'T'HH:mm:ss"
    }
  }
}
